udi_grammar_py/__init__.py
udi_grammar_py/helpers.py
udi_grammar_py/py.typed
udi_grammar_py/spec.py
udi_grammar_py-0.2.7.dist-info/METADATA
udi_grammar_py-0.2.7.dist-info/WHEEL
udi_grammar_py-0.2.7.dist-info/licenses/LICENSE
udi_grammar_py-0.2.7.dist-info/RECORD
