Metadata-Version: 2.4
Name: udi-grammar-py
Version: 0.2.7
Summary: A python library for creating udi-grammar specifications
Project-URL: Homepage, https://github.com/hms-dbmi/udi-grammar-py
Author-email: Devin Lange <devinscottlange@gmail.com>
License: MIT
License-File: LICENSE
Classifier: Environment :: Console
Classifier: Intended Audience :: Developers
Classifier: License :: OSI Approved :: MIT License
Classifier: Operating System :: OS Independent
Classifier: Programming Language :: Python
Classifier: Programming Language :: Python :: 3 :: Only
Classifier: Programming Language :: Python :: 3.13
Requires-Python: >=3.13
